{"cameraMode":{"drawMode":0,"name":"Shaded","section":"Shading Mode"},"sceneLighting":false,"audioPlay":false,"sceneViewState":{"m_AlwaysRefresh":false,"showFog":true,"showSkybox":false,"showFlares":true,"showImageEffects":true,"showParticleSystems":true,"showVisualEffectGraphs":true,"m_FxEnabled":true},"in2DMode":false,"pivot":{"x":531.2500610351563,"y":259.75,"z":0.0},"rotation":{"x":-0.04679175093770027,"y":-0.008395322598516941,"z":0.0004026298993267119,"w":-0.9988824129104614},"size":325.004638671875,"orthographic":false}